MANIFEST.in
README.md
setup.cfg
setup.py
src/iptools/__init__.py
src/iptools/arin.py
src/iptools/ip.py
src/iptools/ip6.py
src/pyiptools.egg-info/PKG-INFO
src/pyiptools.egg-info/SOURCES.txt
src/pyiptools.egg-info/dependency_links.txt
src/pyiptools.egg-info/not-zip-safe
src/pyiptools.egg-info/top_level.txt