Metadata-Version: 1.0
Name: pyiptools
Version: 0.1
Summary: IP address manipulation and ARIN whois lookup library.
Home-page: UNKNOWN
Author: Nadeem Douba
Author-email: ndouba@gmail.com
License: GPL
Platform: UNKNOWN
